setup.py
uniscripts/__init__.py
uniscripts/unidata.py
uniscripts.egg-info/PKG-INFO
uniscripts.egg-info/SOURCES.txt
uniscripts.egg-info/dependency_links.txt
uniscripts.egg-info/top_level.txt